{".class": "MypyFile", "_fullname": "localizer.main_subcommand_list", "is_partial_stub_package": false, "is_stub": false, "names": {".class": "SymbolTable", "__doc__": {".class": "SymbolTableNode", "kind": "Gdef", "node": {".class": "Var", "flags": ["is_ready"], "fullname": "localizer.main_subcommand_list.__doc__", "name": "__doc__", "type": "builtins.str"}}, "__file__": {".class": "SymbolTableNode", "kind": "Gdef", "node": {".class": "Var", "flags": ["is_ready"], "fullname": "localizer.main_subcommand_list.__file__", "name": "__file__", "type": "builtins.str"}}, "__name__": {".class": "SymbolTableNode", "kind": "Gdef", "node": {".class": "Var", "flags": ["is_ready"], "fullname": "localizer.main_subcommand_list.__name__", "name": "__name__", "type": "builtins.str"}}, "__package__": {".class": "SymbolTableNode", "kind": "Gdef", "node": {".class": "Var", "flags": ["is_ready"], "fullname": "localizer.main_subcommand_list.__package__", "name": "__package__", "type": "builtins.str"}}, "_describe": {".class": "SymbolTableNode", "kind": "Gdef", "node": {".class": "FuncDef", "arg_kinds": [0], "arg_names": ["converter"], "flags": [], "fullname": "localizer.main_subcommand_list._describe", "name": "_describe", "type": null}}, "start": {".class": "SymbolTableNode", "kind": "Gdef", "node": {".class": "FuncDef", "arg_kinds": [0, 0], "arg_names": ["args", "converter"], "flags": [], "fullname": "localizer.main_subcommand_list.start", "name": "start", "type": null}}}, "path": "localizer/main_subcommand_list.py"}